data_controller/__init__.py
json_libraries/__init__.py
pg_scripts/__init__.py
pg_scripts/catan/__init__.py
pg_scripts/catan/game_player_rel.py
pg_scripts/catan/games_queries.py
pg_scripts/catan/player_queries.py
unittests/__init__.py
unittests/test_game_player_rel.py
unittests/test_game_queries.py
unittests/test_player_queries.py
utilities/__init__.py
utilities/db_utils/__init__.py
utilities/db_utils/pg_config.py
utilities/db_utils/pg_util.py
utilities/db_utils/query_tools.py
utilities/repo_utils/__init__.py
utilities/repo_utils/logger/__init__.py
utilities/repo_utils/logger/default_logger.py
utilities/repo_utils/scripts/__init__.py
data_config_controller-0.0.1.dist-info/LICENSE
data_config_controller-0.0.1.dist-info/METADATA
data_config_controller-0.0.1.dist-info/WHEEL
data_config_controller-0.0.1.dist-info/top_level.txt
data_config_controller-0.0.1.dist-info/RECORD
