Metadata-Version: 2.1
Name: data-config-controller
Version: 0.0.1
Summary: Database adn config controller 
Home-page: https://github.com/jamberin/data_config_controller
Author: James Beringer
Author-email: jamberin@gmail.com
License: UNKNOWN
Platform: UNKNOWN
Classifier: Programming Language :: Python :: 3
